{
    "1": 1, 
    "5": 1, 
    "6": 0, 
    "_custom_": true, 
    "_ref_": 134277451, 
    "alive_height_box_data": 0, 
    "base_color_mod": 1, 
    "base_tint_color": {
        "__tuple__": true, 
        "items": [
            255, 
            255, 
            255, 
            0.5
        ]
    }, 
    "body_size": 0.5, 
    "collision_box": {
        "__tuple__": true, 
        "items": []
    }, 
    "collision_points_alive": {
        "__tuple__": true, 
        "items": [
            [
                -6, 
                -5
            ], 
            [
                7, 
                6
            ], 
            [
                0, 
                0, 
                0, 
                0, 
                0, 
                0, 
                0, 
                0, 
                0, 
                0, 
                0, 
                0, 
                0, 
                0, 
                0, 
                0, 
                0, 
                0, 
                0, 
                0, 
                0, 
                0, 
                0, 
                0, 
                0, 
                0, 
                0, 
                0, 
                0, 
                0, 
                0, 
                0, 
                0, 
                0, 
                0, 
                0, 
                0, 
                0, 
                0, 
                0, 
                0, 
                0, 
                0, 
                0, 
                0, 
                0, 
                0, 
                0, 
                0, 
                0, 
                0, 
                0, 
                0, 
                0, 
                0, 
                0, 
                32, 
                32, 
                32, 
                32, 
                32, 
                32, 
                0, 
                0, 
                0, 
                0, 
                0, 
                0, 
                0, 
                32, 
                32, 
                32, 
                32, 
                32, 
                32, 
                0, 
                0, 
                0, 
                0, 
                0, 
                0, 
                0, 
                32, 
                32, 
                32, 
                32, 
                32, 
                32, 
                0, 
                0, 
                0, 
                0, 
                0, 
                0, 
                0, 
                32, 
                32, 
                32, 
                32, 
                32, 
                32, 
                0, 
                0, 
                0, 
                0, 
                0, 
                0, 
                0, 
                0, 
                0, 
                0, 
                0, 
                0, 
                0, 
                0, 
                0, 
                0, 
                0, 
                0, 
                0, 
                0, 
                0, 
                0, 
                0, 
                0, 
                0, 
                0, 
                0, 
                0, 
                0, 
                0, 
                0, 
                0, 
                0, 
                0, 
                0, 
                0, 
                0, 
                0, 
                0, 
                0, 
                0, 
                0
            ], 
            0.5
        ]
    }, 
    "collision_points_dead": {
        "__tuple__": true, 
        "items": []
    }, 
    "dead_height_box_data": 0, 
    "default_rate": 1.0, 
    "description": -1040463854, 
    "destroy_delay": 1.0, 
    "destroy_on_die": true, 
    "die_effect_list": [
        {
            "effect": 105015, 
            "offset": {
                "__tuple__": true, 
                "items": [
                    0.0, 
                    0.8, 
                    0.0
                ]
            }, 
            "rotate": {
                "__tuple__": true, 
                "items": [
                    0.0, 
                    0.0, 
                    0.0
                ]
            }, 
            "scale": {
                "__tuple__": true, 
                "items": [
                    1.0, 
                    1.0, 
                    1.0
                ]
            }, 
            "speed": 0.5
        }
    ], 
    "die_on_source_run_out": false, 
    "effect_list": {
        "__tuple__": true, 
        "items": []
    }, 
    "enable_occlusion_perspective": false, 
    "fresnel_color": {
        "__tuple__": true, 
        "items": [
            255, 
            255, 
            255, 
            0.5
        ]
    }, 
    "fresnel_emissive_color_strength": 1, 
    "fresnel_exp": 10, 
    "height_num": 11, 
    "height_offset": 0.25, 
    "hp_max": 1.0, 
    "icon": 100000, 
    "is_ability_target": true, 
    "is_attacked": true, 
    "is_collected": false, 
    "is_selected": true, 
    "is_x_offset": true, 
    "is_z_offset": true, 
    "key": 134277451, 
    "kv": {}, 
    "material_alpha": 0, 
    "material_change": 0, 
    "material_color": {
        "__tuple__": true, 
        "items": [
            255, 
            255, 
            255
        ]
    }, 
    "material_color_intensity": 0, 
    "mini_map_color": {
        "__tuple__": true, 
        "items": [
            255, 
            255, 
            255
        ]
    }, 
    "model": 103332, 
    "model_opacity": 1, 
    "name": -225353885, 
    "passable": false, 
    "receive_decal": false, 
    "show_on_mini_map": true, 
    "sound_event_list": {
        "__tuple__": true, 
        "items": []
    }, 
    "source_desc": -1206799168, 
    "source_item": 10000, 
    "source_nums_init": 0, 
    "source_nums_max": 10000.0, 
    "source_player_prop": "official_res_1", 
    "source_refresh_count": 0, 
    "source_refresh_interval": 5, 
    "source_type": 0, 
    "suffix": "", 
    "tags": {
        "__tuple__": true, 
        "items": []
    }, 
    "uid": "134277451", 
    "use_base_tint_color": false, 
    "use_fresnel": 0, 
    "width_num": 13, 
    "width_offset": 0.25
}